<?xml version="1.0"?>
<response><objects><object><recordsretentionpolicy>1</recordsretentionpolicy><distributes990toboard>1</distributes990toboard><fundraising_efficiency>0.140000000000000</fundraising_efficiency><whistleblowerpolicy>1</whistleblowerpolicy><total_revenue>1254604.00</total_revenue><privacy_status>0</privacy_status><mission>Founded in the year 1985, The Make-A-Wish Foundation of Central New York's mission is to grant the wishes of children with life-threatening medical conditions to enrich the human experience with hope, strength, and joy. Fulfilling a child's wish provides a joyful and meaningful experience that benefits both the child and the family. In our chapter, we currently have approximately 300 volunteers and welcome other interested individuals. The Make-A-Wish Foundation of Central New York has granted more than 1,200 wishes. Nationally, the Make-A-Wish Foundation has granted nearly 185,000 wishes.</mission><charity_name>Make-A-Wish Foundation of Central New York</charity_name><current_ceo_title>President, CEO</current_ceo_title><cob_name>Joseph Chirco</cob_name><auditedfinancial_status>0</auditedfinancial_status><orgid>13272</orgid><administration_expenses>100594.00</administration_expenses><accountability_rating>3</accountability_rating><administration_expenses_ratio>0.090000000000000</administration_expenses_ratio><category>Health</category><city>Syracuse</city><cob_title>Chair</cob_title><materialdiversionofassets>1</materialdiversionofassets><conflictofinterestpolicy>1</conflictofinterestpolicy><zip>13057</zip><primary_revenue_growth>0.086000000000000</primary_revenue_growth><overall_score>52.320000000000000</overall_score><loanstoofficers>1</loanstoofficers><state>NY</state><reportsceoandsalary>1</reportsceoandsalary><boardcomposition>1</boardcomposition><compensatesboard>1</compensatesboard><cause>Patient and Family Support</cause><program_expenses_growth>-0.028000000000000</program_expenses_growth><overall_rating>3</overall_rating><program_expenses>843983.00</program_expenses><program_expenses_ratio>0.755000000000000</program_expenses_ratio><stafflist_status>1</stafflist_status><boardlist_status>1</boardlist_status><financial_score>47.55</financial_score><street_address_1>5005 Campuswood Drive</street_address_1><accountability_score>59.00</accountability_score><street_address_2></street_address_2><current_ceo_name>Diane E. Kuppermann</current_ceo_name><ein>222572086</ein><total_expenses>1117262.00</total_expenses><financial_rating>2</financial_rating><fundraising_expenses_ratio>0.154000000000000</fundraising_expenses_ratio><boardmeetingminutes>1</boardmeetingminutes><total_net_assets>1022073.00</total_net_assets><fundraising_expenses>172685.00</fundraising_expenses><tag_line>Share the power of a wish</tag_line><independentaudit>1</independentaudit><working_capital_ratio>0.870000000000000</working_capital_ratio><ceocompensationprocedure>1</ceocompensationprocedure><form990_status>0</form990_status><loanstoorfromofficers>1</loanstoorfromofficers><resource_uri>http://api.charitynavigator.org/api/v1/organizations/13272/</resource_uri></object></objects></response>
