<?xml version="1.0"?>
<response><objects><object><recordsretentionpolicy>1</recordsretentionpolicy><distributes990toboard>1</distributes990toboard><fundraising_efficiency>0.150000000000000</fundraising_efficiency><whistleblowerpolicy>1</whistleblowerpolicy><total_revenue>4666718.00</total_revenue><privacy_status>1</privacy_status><mission>The Taproot Foundation strengthens nonprofits by engaging business professionals in service. We seek to harness human capital to improve the human condition. Historically, pro bono work has been an unreliable source of support for the nonprofit sector. The Taproot Foundation has solved this problem by creating the structure necessary to consistently deliver high-quality pro bono work in volume. Since 2001, we have: awarded over 1,270 pro bono projects, supported over 1,000 nonprofit organizations, whose programs collectively serve approximately 45 million Americans in need, recruited over 7,200 business professionals to volunteer their skills, delivered over 700,000 hours of pro bono service, and donated more than $58 million worth of professional services.</mission><charity_name>Taproot Foundation</charity_name><current_ceo_title>President</current_ceo_title><cob_name>Sylvia Reynolds</cob_name><auditedfinancial_status>1</auditedfinancial_status><orgid>11217</orgid><administration_expenses>292735.00</administration_expenses><accountability_rating>4</accountability_rating><administration_expenses_ratio>0.068000000000000</administration_expenses_ratio><category>Public Benefit</category><city>San Francisco</city><cob_title>Chair</cob_title><materialdiversionofassets>1</materialdiversionofassets><conflictofinterestpolicy>1</conflictofinterestpolicy><zip>94102</zip><primary_revenue_growth>0.131000000000000</primary_revenue_growth><overall_score>63.170000000000000</overall_score><loanstoofficers>1</loanstoofficers><state>CA</state><reportsceoandsalary>1</reportsceoandsalary><boardcomposition>1</boardcomposition><compensatesboard>1</compensatesboard><cause>Advocacy and Civil Rights</cause><program_expenses_growth>0.211000000000000</program_expenses_growth><overall_rating>4</overall_rating><program_expenses>3363042.00</program_expenses><program_expenses_ratio>0.785000000000000</program_expenses_ratio><stafflist_status>1</stafflist_status><boardlist_status>1</boardlist_status><financial_score>60.35</financial_score><street_address_1>466 Geary Street</street_address_1><accountability_score>70.00</accountability_score><street_address_2>Suite 200</street_address_2><current_ceo_name>Aaron Hurst</current_ceo_name><ein>912162645</ein><total_expenses>4283636.00</total_expenses><financial_rating>4</financial_rating><fundraising_expenses_ratio>0.146000000000000</fundraising_expenses_ratio><boardmeetingminutes>1</boardmeetingminutes><total_net_assets>2179176.00</total_net_assets><fundraising_expenses>627859.00</fundraising_expenses><tag_line>Do it pro bono</tag_line><independentaudit>1</independentaudit><working_capital_ratio>0.500000000000000</working_capital_ratio><ceocompensationprocedure>1</ceocompensationprocedure><form990_status>1</form990_status><loanstoorfromofficers>1</loanstoorfromofficers><resource_uri>http://api.charitynavigator.org/api/v1/organizations/11217/</resource_uri></object></objects></response>
