<?xml version="1.0"?>
<response><objects><object><recordsretentionpolicy>1</recordsretentionpolicy><distributes990toboard>1</distributes990toboard><fundraising_efficiency>0.130000000000000</fundraising_efficiency><whistleblowerpolicy>1</whistleblowerpolicy><total_revenue>8559559.00</total_revenue><privacy_status>1</privacy_status><mission>Founded in 1972, The Alexander Muss Institute for Israel Education (AMIIE) works to provide a superior Israel education experience to learners of all ages in Israel and within communities throughout North America and abroad. The Institute promotes, builds and strengthens lifelong bonds between Jews and Israel through education, experiences and understanding. We offer a menu of exciting Israel education programs for teens, adults, Family and Bar/Bat Mitzvah tours, Jewish Day Schools, Community Groups and more. Our Israel education programs, taught by our renowned faculty, bring Israel to life for lay and professional leaders and learners of all ages. Every program offered by AMIIE will be customized to meet the needs and goals of specific schools and community groups.</mission><charity_name>Alexander Muss Institute for Israel Education</charity_name><current_ceo_title>Chief Executive Officer</current_ceo_title><cob_name>Stephen Muss</cob_name><auditedfinancial_status>1</auditedfinancial_status><orgid>3821</orgid><administration_expenses>787869.00</administration_expenses><accountability_rating>4</accountability_rating><administration_expenses_ratio>0.102000000000000</administration_expenses_ratio><category>International</category><city>Rockville Centre</city><cob_title>Chairperson</cob_title><materialdiversionofassets>1</materialdiversionofassets><conflictofinterestpolicy>1</conflictofinterestpolicy><zip>11570</zip><primary_revenue_growth>0.158000000000000</primary_revenue_growth><overall_score>65.500000000000000</overall_score><loanstoofficers>1</loanstoofficers><state>NY</state><reportsceoandsalary>1</reportsceoandsalary><boardcomposition>1</boardcomposition><compensatesboard>1</compensatesboard><cause>Foreign Charity Support Organizations</cause><program_expenses_growth>0.156000000000000</program_expenses_growth><overall_rating>4</overall_rating><program_expenses>6622252.00</program_expenses><program_expenses_ratio>0.864000000000000</program_expenses_ratio><stafflist_status>1</stafflist_status><boardlist_status>1</boardlist_status><financial_score>63.64</financial_score><street_address_1>78 Randall Avenue</street_address_1><accountability_score>70.00</accountability_score><street_address_2></street_address_2><current_ceo_name>Gideon Shavit</current_ceo_name><ein>590173782</ein><total_expenses>7659974.00</total_expenses><financial_rating>4</financial_rating><fundraising_expenses_ratio>0.032000000000000</fundraising_expenses_ratio><boardmeetingminutes>1</boardmeetingminutes><total_net_assets>5825203.00</total_net_assets><fundraising_expenses>249853.00</fundraising_expenses><tag_line>Providing a superior Israel education experience</tag_line><independentaudit>1</independentaudit><working_capital_ratio>0.740000000000000</working_capital_ratio><ceocompensationprocedure>1</ceocompensationprocedure><form990_status>1</form990_status><loanstoorfromofficers>1</loanstoorfromofficers><resource_uri>http://api.charitynavigator.org/api/v1/organizations/3821/</resource_uri></object></objects></response>
