<?xml version="1.0"?>
<response><objects><object><recordsretentionpolicy>1</recordsretentionpolicy><distributes990toboard>1</distributes990toboard><fundraising_efficiency>0.020000000000000</fundraising_efficiency><whistleblowerpolicy>1</whistleblowerpolicy><total_revenue>12254371.00</total_revenue><privacy_status>1</privacy_status><mission>EarthShare engages individuals and organizations in creating a healthy and sustainable environment. Founded by its member charities in 1988, EarthShare is an opportunity for environmentally-conscious employees and workplaces to support hundreds of environmental groups through workplace payroll contribution campaigns. Today EarthShare represents and supports more than 400 of America's most respected environmental and conservation charities, including 39 national organizations and hundreds of local groups in 18 affiliate states. EarthShare's member organizations work hard every day to safeguard your health and the environment by combating global warming, protecting ancient forests, protecting our water from toxic contaminants, saving endangered species and so much more.</mission><charity_name>EarthShare</charity_name><current_ceo_title>President and CEO</current_ceo_title><cob_name>Marci Reed</cob_name><auditedfinancial_status>1</auditedfinancial_status><orgid>3637</orgid><administration_expenses>374544.00</administration_expenses><accountability_rating>4</accountability_rating><administration_expenses_ratio>0.029000000000000</administration_expenses_ratio><category>Public Benefit</category><city>Bethesda</city><cob_title>Board Chair                                       </cob_title><materialdiversionofassets>1</materialdiversionofassets><conflictofinterestpolicy>1</conflictofinterestpolicy><zip>20814</zip><primary_revenue_growth>-0.029000000000000</primary_revenue_growth><overall_score>54.670000000000000</overall_score><loanstoofficers>1</loanstoofficers><state>MD</state><reportsceoandsalary>1</reportsceoandsalary><boardcomposition>1</boardcomposition><compensatesboard>1</compensatesboard><cause>Fundraising Organizations</cause><program_expenses_growth>-0.026000000000000</program_expenses_growth><overall_rating>3</overall_rating><program_expenses>11816720.00</program_expenses><program_expenses_ratio>0.946000000000000</program_expenses_ratio><stafflist_status>1</stafflist_status><boardlist_status>1</boardlist_status><financial_score>48.33</financial_score><street_address_1>7735 Old Georgetown Road</street_address_1><accountability_score>70.00</accountability_score><street_address_2>Suite 900</street_address_2><current_ceo_name>Kalman Stein</current_ceo_name><ein>521601960</ein><total_expenses>12489525.00</total_expenses><financial_rating>2</financial_rating><fundraising_expenses_ratio>0.023000000000000</fundraising_expenses_ratio><boardmeetingminutes>1</boardmeetingminutes><total_net_assets>440790.00</total_net_assets><fundraising_expenses>298261.00</fundraising_expenses><tag_line>One environment . . .one simple way to care for it</tag_line><independentaudit>1</independentaudit><working_capital_ratio>0.030000000000000</working_capital_ratio><ceocompensationprocedure>1</ceocompensationprocedure><form990_status>1</form990_status><loanstoorfromofficers>1</loanstoorfromofficers><resource_uri>http://api.charitynavigator.org/api/v1/organizations/3637/</resource_uri></object></objects></response>
