<?xml version="1.0"?>
<response><objects><object><recordsretentionpolicy>1</recordsretentionpolicy><distributes990toboard>1</distributes990toboard><fundraising_efficiency>0.110000000000000</fundraising_efficiency><whistleblowerpolicy>1</whistleblowerpolicy><total_revenue>8002451.00</total_revenue><privacy_status>1</privacy_status><mission>Founded in 1942, AMG (Advancing the Ministries of the Gospel) International is an evangelical mission and relief agency, working in approximately 50 countries of the world. Our mission is clear: to give each person at least one opportunity to hear and respond to the gospel. At AMG, we endeavor to meet people at the point of their need whether it be hunger, sickness, or hopelessness, and show them Jesus as the only answer to the problems of this life and the only hope for eternal life. Our Christian missionary activities include children's work and relief, newspaper and magazine evangelism, radio and television evangelism, and missionary projects and support.</mission><charity_name>AMG International</charity_name><current_ceo_title>President</current_ceo_title><cob_name>William S. Hardin</cob_name><auditedfinancial_status>1</auditedfinancial_status><orgid>3204</orgid><administration_expenses>223840.00</administration_expenses><accountability_rating>4</accountability_rating><administration_expenses_ratio>0.032000000000000</administration_expenses_ratio><category>Religion</category><city>Chattanooga</city><cob_title>Chairman of the Board</cob_title><materialdiversionofassets>1</materialdiversionofassets><conflictofinterestpolicy>1</conflictofinterestpolicy><zip>37421</zip><primary_revenue_growth>0.009000000000000</primary_revenue_growth><overall_score>64.710000000000000</overall_score><loanstoofficers>1</loanstoofficers><state>TN</state><reportsceoandsalary>1</reportsceoandsalary><boardcomposition>1</boardcomposition><compensatesboard>1</compensatesboard><cause>Religious Activities</cause><program_expenses_growth>0.041000000000000</program_expenses_growth><overall_rating>4</overall_rating><program_expenses>5810830.00</program_expenses><program_expenses_ratio>0.850000000000000</program_expenses_ratio><stafflist_status>1</stafflist_status><boardlist_status>1</boardlist_status><financial_score>62.52</financial_score><street_address_1>6815 Shallowford Road</street_address_1><accountability_score>70.00</accountability_score><street_address_2></street_address_2><current_ceo_name>Paul Jenks</current_ceo_name><ein>131766596</ein><total_expenses>6836226.00</total_expenses><financial_rating>4</financial_rating><fundraising_expenses_ratio>0.117000000000000</fundraising_expenses_ratio><boardmeetingminutes>1</boardmeetingminutes><total_net_assets>10512691.00</total_net_assets><fundraising_expenses>801556.00</fundraising_expenses><tag_line>Advancing the ministries of the Gospel</tag_line><independentaudit>1</independentaudit><working_capital_ratio>1.410000000000000</working_capital_ratio><ceocompensationprocedure>1</ceocompensationprocedure><form990_status>1</form990_status><loanstoorfromofficers>1</loanstoorfromofficers><resource_uri>http://api.charitynavigator.org/api/v1/organizations/3204/</resource_uri></object></objects></response>
