<?xml version="1.0"?>
<response><objects><object><Category>Human Services</Category><city>New York</city><OverallRtg>3.0</OverallRtg><Charity_Name>Baby Buggy</Charity_Name><OverallScore>52.48</OverallScore><state>NY</state><OrgId>10256</OrgId><Rank></Rank><ein>311777082</ein><Cause>Social Services</Cause><Tag_Line>Love. Recycled.</Tag_Line><resource_uri></resource_uri></object><object><Category>Health</Category><city>New York</city><OverallRtg>3.0</OverallRtg><Charity_Name>The Bachmann-Strauss Dystonia &amp; Parkinson Foundation</Charity_Name><OverallScore>52.96</OverallScore><state>NY</state><OrgId>12627</OrgId><Rank></Rank><ein>133804248</ein><Cause>Diseases, Disorders, and Disciplines</Cause><Tag_Line>Encouraging new research and scientists in the fields of dystonia and Parkinson disease</Tag_Line><resource_uri></resource_uri></object><object><Category>Religion</Category><city>Lincoln</city><OverallRtg>2.0</OverallRtg><Charity_Name>Back to the Bible</Charity_Name><OverallScore>43.07</OverallScore><state>NE</state><OrgId>3762</OrgId><Rank></Rank><ein>470405317</ein><Cause>Religious Media and Broadcasting</Cause><Tag_Line>Leading people into a dynamic relationship with God</Tag_Line><resource_uri></resource_uri></object><object><Category>Public Benefit</Category><city>Lincoln</city><OverallRtg>2.0</OverallRtg><Charity_Name>Back to the Bible Foundation</Charity_Name><OverallScore>42.21</OverallScore><state>NE</state><OrgId>9058</OrgId><Rank></Rank><ein>476022615</ein><Cause>Fundraising Organizations</Cause><Tag_Line>Increasing public support to benefit Back to the Bible</Tag_Line><resource_uri></resource_uri></object><object><Category>Human Services</Category><city>Bloomington</city><OverallRtg>3.0</OverallRtg><Charity_Name>Backstreet Missions</Charity_Name><OverallScore>50.49</OverallScore><state>IN</state><OrgId>10933</OrgId><Rank></Rank><ein>351965051</ein><Cause>Homeless Services</Cause><Tag_Line>A Christ-centered ministry extending Christ's love to the homeless</Tag_Line><resource_uri></resource_uri></object><object><Category>International</Category><city>Irving</city><OverallRtg>3.0</OverallRtg><Charity_Name>Baitulmaal</Charity_Name><OverallScore>57.24</OverallScore><state>TX</state><OrgId>12999</OrgId><Rank></Rank><ein>200942434</ein><Cause>Development and Relief Services</Cause><Tag_Line>Reaching out to those in need around the world</Tag_Line><resource_uri></resource_uri></object><object><Category>Human Services</Category><city>Bakersfield</city><OverallRtg>3.0</OverallRtg><Charity_Name>Bakersfield Rescue Mission</Charity_Name><OverallScore>51.51</OverallScore><state>CA</state><OrgId>9803</OrgId><Rank></Rank><ein>951890705</ein><Cause>Homeless Services</Cause><Tag_Line>Where love is in action</Tag_Line><resource_uri></resource_uri></object><object><Category>Health</Category><city>Evanston</city><OverallRtg>3.0</OverallRtg><Charity_Name>The Balanced Mind Foundation</Charity_Name><OverallScore>58.03</OverallScore><state>IL</state><OrgId>9970</OrgId><Rank></Rank><ein>364302941</ein><Cause>Diseases, Disorders, and Disciplines</Cause><Tag_Line>Support, empower, advocate, create, educate, inspire, heal</Tag_Line><resource_uri></resource_uri></object><object><Category>Arts, Culture, Humanities</Category><city>New York</city><OverallRtg>2.0</OverallRtg><Charity_Name>Ballet Hispanico</Charity_Name><OverallScore>49.04</OverallScore><state>NY</state><OrgId>8939</OrgId><Rank></Rank><ein>132685755</ein><Cause>Performing Arts</Cause><Tag_Line>The foremost dance representative of Hispanic culture in the United States</Tag_Line><resource_uri></resource_uri></object><object><Category>Arts, Culture, Humanities</Category><city>San Jose</city><OverallRtg>3.0</OverallRtg><Charity_Name>Ballet San Jose</Charity_Name><OverallScore>51.95</OverallScore><state>CA</state><OrgId>10654</OrgId><Rank></Rank><ein>942894849</ein><Cause>Performing Arts</Cause><Tag_Line>Providing the South Bay with theatrically produced ballet and professional dance education</Tag_Line><resource_uri></resource_uri></object><object><Category>Arts, Culture, Humanities</Category><city>New York</city><OverallRtg>2.0</OverallRtg><Charity_Name>Ballet Tech Foundation</Charity_Name><OverallScore>48.51</OverallScore><state>NY</state><OrgId>8216</OrgId><Rank></Rank><ein>132773475</ein><Cause>Performing Arts</Cause><Tag_Line>Presenting professional ballet and training tomorrow's dancers</Tag_Line><resource_uri></resource_uri></object><object><Category>Arts, Culture, Humanities</Category><city>Salt Lake City</city><OverallRtg>3.0</OverallRtg><Charity_Name>Ballet West</Charity_Name><OverallScore>54.0</OverallScore><state>UT</state><OrgId>8719</OrgId><Rank></Rank><ein>870264274</ein><Cause>Performing Arts</Cause><Tag_Line>An American pioneer in the world of dance</Tag_Line><resource_uri></resource_uri></object><object><Category>Arts, Culture, Humanities</Category><city>Baltimore</city><OverallRtg>3.0</OverallRtg><Charity_Name>Baltimore &amp; Ohio Railroad Museum</Charity_Name><OverallScore>55.18</OverallScore><state>MD</state><OrgId>8976</OrgId><Rank></Rank><ein>521535426</ein><Cause>Museums</Cause><Tag_Line>America's railroad museum</Tag_Line><resource_uri></resource_uri></object><object><Category>Education</Category><city>Baltimore</city><OverallRtg>2.0</OverallRtg><Charity_Name>Baltimore Clayworks</Charity_Name><OverallScore>47.39</OverallScore><state>MD</state><OrgId>11183</OrgId><Rank></Rank><ein>521409133</ein><Cause>Other Education Programs and Services</Cause><Tag_Line>Providing outstanding artistic, educational, and collaborative programs in ceramic arts</Tag_Line><resource_uri></resource_uri></object><object><Category>Public Benefit</Category><city>Baltimore</city><OverallRtg>3.0</OverallRtg><Charity_Name>Baltimore Community Foundation</Charity_Name><OverallScore>53.26</OverallScore><state>MD</state><OrgId>5130</OrgId><Rank></Rank><ein>237180620</ein><Cause>Community Foundations</Cause><Tag_Line>Improving the quality of life in Baltimore</Tag_Line><resource_uri></resource_uri></object><object><Category>Arts, Culture, Humanities</Category><city>Baltimore</city><OverallRtg>3.0</OverallRtg><Charity_Name>The Baltimore Museum of Art</Charity_Name><OverallScore>56.93</OverallScore><state>MD</state><OrgId>3337</OrgId><Rank></Rank><ein>526000162</ein><Cause>Museums</Cause><Tag_Line>Inspiring creativity, encouraging learning, and fostering human understanding</Tag_Line><resource_uri></resource_uri></object><object><Category>Education</Category><city>Baltimore</city><OverallRtg>3.0</OverallRtg><Charity_Name>Baltimore Reads</Charity_Name><OverallScore>59.73</OverallScore><state>MD</state><OrgId>7689</OrgId><Rank></Rank><ein>521626015</ein><Cause>Other Education Programs and Services</Cause><Tag_Line>Providing skills for life</Tag_Line><resource_uri></resource_uri></object><object><Category>Arts, Culture, Humanities</Category><city>Baltimore</city><OverallRtg>3.0</OverallRtg><Charity_Name>Baltimore Symphony Orchestra</Charity_Name><OverallScore>54.03</OverallScore><state>MD</state><OrgId>3338</OrgId><Rank></Rank><ein>520629696</ein><Cause>Performing Arts</Cause><Tag_Line>Providing symphonic concerts, cultural and educational resources</Tag_Line><resource_uri></resource_uri></object><object><Category>Animals</Category><city>Bangor</city><OverallRtg>2.0</OverallRtg><Charity_Name>Bangor Humane Society</Charity_Name><OverallScore>42.86</OverallScore><state>ME</state><OrgId>10965</OrgId><Rank></Rank><ein>010215910</ein><Cause>Animal Rights, Welfare, and Services</Cause><Tag_Line>The animal place</Tag_Line><resource_uri></resource_uri></object><object><Category>Human Services</Category><city>Thomasville</city><OverallRtg>3.0</OverallRtg><Charity_Name>Baptist Children's Homes of North Carolina</Charity_Name><OverallScore>51.8</OverallScore><state>NC</state><OrgId>5501</OrgId><Rank></Rank><ein>560547499</ein><Cause>Children's and Family Services</Cause><Tag_Line>Helping hurting children . . .healing broken families</Tag_Line><resource_uri></resource_uri></object></objects></response>
